aeslib/__init__.py
aeslib/Tools/__init__.py
aeslib/Tools/loop_functions.py
aeslib/data_engineering/__init__.py
aeslib/data_engineering/azure_tools.py
aeslib/data_engineering/bazefield.py
aeslib/data_science/__init__.py
aeslib/data_science/data_corrector.py
aeslib/data_science/dataframe_tools.py
aeslib/data_science/interval_analysis.py
aeslib/data_science/missing_data_analysis.py
aeslib/data_science/series_tools.py
aeslib/data_science/utility.py
aeslib/data_science/visualization.py
aestene_lib-0.1.4.dist-info/LICENSE
aestene_lib-0.1.4.dist-info/METADATA
aestene_lib-0.1.4.dist-info/WHEEL
aestene_lib-0.1.4.dist-info/top_level.txt
aestene_lib-0.1.4.dist-info/RECORD
